odoo8_addon_sale_order_import-8.0.1.1.0-nspkg.pth
odoo_addons/sale_order_import/README.rst
odoo_addons/sale_order_import/__init__.py
odoo_addons/sale_order_import/__openerp__.py
odoo_addons/sale_order_import/i18n/fr.po
odoo_addons/sale_order_import/i18n/pt_BR.po
odoo_addons/sale_order_import/i18n/sale_order_import.pot
odoo_addons/sale_order_import/models/__init__.py
odoo_addons/sale_order_import/models/sale.py
odoo_addons/sale_order_import/static/description/icon.png
odoo_addons/sale_order_import/wizard/__init__.py
odoo_addons/sale_order_import/wizard/sale_order_import.py
odoo_addons/sale_order_import/wizard/sale_order_import_view.xml
odoo8_addon_sale_order_import-8.0.1.1.0.dist-info/METADATA
odoo8_addon_sale_order_import-8.0.1.1.0.dist-info/WHEEL
odoo8_addon_sale_order_import-8.0.1.1.0.dist-info/namespace_packages.txt
odoo8_addon_sale_order_import-8.0.1.1.0.dist-info/top_level.txt
odoo8_addon_sale_order_import-8.0.1.1.0.dist-info/RECORD
